tensorflow_privacy/privacy/privacy_tests/__init__.py
tensorflow_privacy/privacy/privacy_tests/epsilon_lower_bound.py
tensorflow_privacy/privacy/privacy_tests/epsilon_lower_bound_test.py
tensorflow_privacy/privacy/privacy_tests/utils.py
tensorflow_privacy/privacy/privacy_tests/utils_test.py
tensorflow_privacy/privacy/privacy_tests/version.py
tensorflow_privacy/privacy/privacy_tests/membership_inference_attack/__init__.py
tensorflow_privacy/privacy/privacy_tests/membership_inference_attack/advanced_mia.py
tensorflow_privacy/privacy/privacy_tests/membership_inference_attack/advanced_mia_example.py
tensorflow_privacy/privacy/privacy_tests/membership_inference_attack/advanced_mia_test.py
tensorflow_privacy/privacy/privacy_tests/membership_inference_attack/data_structures.py
tensorflow_privacy/privacy/privacy_tests/membership_inference_attack/data_structures_test.py
tensorflow_privacy/privacy/privacy_tests/membership_inference_attack/dataset_slicing.py
tensorflow_privacy/privacy/privacy_tests/membership_inference_attack/dataset_slicing_test.py
tensorflow_privacy/privacy/privacy_tests/membership_inference_attack/keras_evaluation.py
tensorflow_privacy/privacy/privacy_tests/membership_inference_attack/keras_evaluation_example.py
tensorflow_privacy/privacy/privacy_tests/membership_inference_attack/keras_evaluation_test.py
tensorflow_privacy/privacy/privacy_tests/membership_inference_attack/membership_inference_attack.py
tensorflow_privacy/privacy/privacy_tests/membership_inference_attack/membership_inference_attack_test.py
tensorflow_privacy/privacy/privacy_tests/membership_inference_attack/models.py
tensorflow_privacy/privacy/privacy_tests/membership_inference_attack/models_test.py
tensorflow_privacy/privacy/privacy_tests/membership_inference_attack/plotting.py
tensorflow_privacy/privacy/privacy_tests/membership_inference_attack/privacy_report.py
tensorflow_privacy/privacy/privacy_tests/membership_inference_attack/privacy_report_test.py
tensorflow_empirical_privacy-0.1.0.dist-info/LICENSE
tensorflow_empirical_privacy-0.1.0.dist-info/METADATA
tensorflow_empirical_privacy-0.1.0.dist-info/WHEEL
tensorflow_empirical_privacy-0.1.0.dist-info/top_level.txt
tensorflow_empirical_privacy-0.1.0.dist-info/RECORD
